{
  "project_info": {
    "project_number": "309739659484",
    "project_id": "pressensiapps",
    "storage_bucket": "pressensiapps.appspot.com"
  },
  "client": [
    {
      "client_info": {
        "mobilesdk_app_id": "1:309739659484:android:1aa7970eea5dd0148a5419",
        "android_client_info": {
          "package_name": "com.folkatech.pressensiapps"
        }
      },
      "oauth_client": [
        {
          "client_id": "309739659484-aalouuvt1jf0e3t50k9r1b4i5hcuqjji.apps.googleusercontent.com",
          "client_type": 1,
          "android_info": {
            "package_name": "com.folkatech.pressensiapps",
            "certificate_hash": "f29a2f85f6fa6cfab21252138aaf8b8193d903cc"
          }
        },
        {
          "client_id": "309739659484-cjcp8hpc8mea9v44vejjlcmlr0dig95c.apps.googleusercontent.com",
          "client_type": 1,
          "android_info": {
            "package_name": "com.folkatech.pressensiapps",
            "certificate_hash": "b0c0c7fcbae47638ec0b5cb5ec875b69e6948192"
          }
        },
        {
          "client_id": "309739659484-hvlecgb9nh3pbg18f8t80hr9glgner50.apps.googleusercontent.com",
          "client_type": 1,
          "android_info": {
            "package_name": "com.folkatech.pressensiapps",
            "certificate_hash": "2e2a3cedabf84c396925e26b9530994b128c87f4"
          }
        },
        {
          "client_id": "309739659484-holghcds4jumli4jf2v3chrtasni9ivq.apps.googleusercontent.com",
          "client_type": 3
        }
      ],
      "api_key": [
        {
          "current_key": "AIzaSyChgRmhMxnuKAuTY4W1wtal0rx58kNkubo"
        }
      ],
      "services": {
        "appinvite_service": {
          "other_platform_oauth_client": [
            {
              "client_id": "309739659484-93re8ilqskmfc3h2ccdn9rm4ev7h9sgp.apps.googleusercontent.com",
              "client_type": 3
            }
          ]
        }
      }
    }
  ],
  "configuration_version": "1"
}